dbt/adapters/conveyorsnowflake/__init__.py
dbt/adapters/conveyorsnowflake/__version__.py
dbt/adapters/conveyorsnowflake/connections.py
dbt/include/conveyorsnowflake/__init__.py
dbt/include/conveyorsnowflake/dbt_project.yml
dbt_conveyor_snowflake-1.8.0.dist-info/LICENSE
dbt_conveyor_snowflake-1.8.0.dist-info/METADATA
dbt_conveyor_snowflake-1.8.0.dist-info/WHEEL
dbt_conveyor_snowflake-1.8.0.dist-info/top_level.txt
dbt_conveyor_snowflake-1.8.0.dist-info/RECORD
